<?xml version="1.0" encoding="utf-8"?>
<manifest xmlns="http://tizen.org/ns/packages" package="ise-default" type="rpm" version="1.1.16" install-location="internal-only">
<author/>
<description/>
<label>Tizen keyboard</label>
<icon/>
<ui-application appid="ise-default" exec="/usr/lib/scim-1.0/scim-helper-launcher" nodisplay="true" taskmanage="false" multiple="false" type="capp" hw-acceleration="use-system-setting" mainapp="true">
    <category name="http://tizen.org/category/ime"/>
    <label>Tizen keyboard</label>
    <label xml:lang="ar-ae">لوحة مفاتيح Tizen</label>
    <label xml:lang="as-in">Tizen কীব'ৰ্ড</label>
    <label xml:lang="az-az">Tizen klaviaturası</label>
    <label xml:lang="bg-bg">Клавиатура на Tizen</label>
    <label xml:lang="bn-in">Tizen কীবোর্ড</label>
    <label xml:lang="ca-es">Teclat de Tizen</label>
    <label xml:lang="cs-cz">Klávesnice Tizen</label>
    <label xml:lang="da-dk">Tizen-tastatur</label>
    <label xml:lang="de-de">Tizen-Tastatur</label>
    <label xml:lang="el-gr">Πληκτρολόγιο Tizen</label>
    <label xml:lang="en-gb">Tizen keyboard</label>
    <label xml:lang="en-ph">Tizen keyboard</label>
    <label xml:lang="en-us">Tizen keyboard</label>
    <label xml:lang="es-es">Teclado de Tizen</label>
    <label xml:lang="es-mx">Teclado Tizen</label>
    <label xml:lang="et-ee">Tizeni klaviatuur</label>
    <label xml:lang="eu-es">Tizen teklatua</label>
    <label xml:lang="fa-ir">صفحه کلید Tizen</label>
    <label xml:lang="fi-fi">Tizen-näppäimistö</label>
    <label xml:lang="fr-ca">Clavier Tizen</label>
    <label xml:lang="fr-fr">Clavier Tizen</label>
    <label xml:lang="ga-ie">Eochairchlár Tizen</label>
    <label xml:lang="gl-es">Teclado Tizen</label>
    <label xml:lang="gu-in">Tizen કીબોર્ડ</label>
    <label xml:lang="he-il">מקלדת Tizen</label>
    <label xml:lang="hi-in">Tizen कीबोर्ड</label>
    <label xml:lang="hr-hr">Tipkovnica za Tizen</label>
    <label xml:lang="hu-hu">Tizen-billentyűzet</label>
    <label xml:lang="hy-am">Tizen ստեղնաշար</label>
    <label xml:lang="id-id">Keyboard Tizen</label>
    <label xml:lang="is-is">Tizen-lyklaborð</label>
    <label xml:lang="it-it">Tastiera Tizen</label>
    <label xml:lang="ja-jp">Tizenキーボード</label>
    <label xml:lang="ka-ge">Tizen კლავიატურა</label>
    <label xml:lang="kk-kz">Tizen пернетақтасы</label>
    <label xml:lang="km-kh">ក្ដារចុច Tizen</label>
    <label xml:lang="kn-in">Tizen ಕೀಬೋರ್ಡ್</label>
    <label xml:lang="ko-kr">타이젠 키보드</label>
    <label xml:lang="ky-kg">Tizen клавиатурасы</label>
    <label xml:lang="lo-la">ຄີບອດ Tizen</label>
    <label xml:lang="lt-lt">„Tizen“ klaviatūra</label>
    <label xml:lang="lv-lv">Tizen tastatūra</label>
    <label xml:lang="mk-mk">Тастатура Tizen</label>
    <label xml:lang="ml-in">Tizen കീബോർഡ്</label>
    <label xml:lang="mn-mn">Tizen гар</label>
    <label xml:lang="mr-in">Tizen कीबोर्ड</label>
    <label xml:lang="ms-my">Papan kekunci Tizen</label>
    <label xml:lang="my-mm">Tizen ကီးဘုတ်</label>
    <label xml:lang="nb-no">Tizen-tastatur</label>
    <label xml:lang="ne-np">Tizen कीबोर्ड</label>
    <label xml:lang="nl-nl">Tizen-toetsenbord</label>
    <label xml:lang="or-in">Tizen କୀବୋର୍ଡ</label>
    <label xml:lang="pa-in">Tizen ਕੀਬੋਰਡ</label>
    <label xml:lang="pl-pl">Klawiatura Tizen</label>
    <label xml:lang="pt-br">Teclado Tizen</label>
    <label xml:lang="pt-pt">Teclado Tizen</label>
    <label xml:lang="ro-ro">Tastatură Tizen</label>
    <label xml:lang="ru-ru">Клавиатура Tizen</label>
    <label xml:lang="si-lk">Tizen යතුරු පුවරුව</label>
    <label xml:lang="sk-sk">Klávesnica Tizen</label>
    <label xml:lang="sl-si">Tipkovnica Tizen</label>
    <label xml:lang="sq-al">Tastiera Tizen</label>
    <label xml:lang="sr-rs">Tizen tastatura</label>
    <label xml:lang="sv-se">Tizen-tangentbord</label>
    <label xml:lang="ta-in">Tizen விசைப்பலகை</label>
    <label xml:lang="te-in">Tizen కీబోర్డ్</label>
    <label xml:lang="tg-tj">Клавиатураи Tizen</label>
    <label xml:lang="th-th">แป้นพิมพ์ Tizen</label>
    <label xml:lang="tk-tm">Tizen klawiatura</label>
    <label xml:lang="tl-ph">Tizen keyboard</label>
    <label xml:lang="tr-tr">Tizen klavye</label>
    <label xml:lang="uk-ua">Клавіатура Tizen</label>
    <label xml:lang="ur-pk">Tizen کی بورڈ</label>
    <label xml:lang="uz-uz">Tizen klaviaturasi</label>
    <label xml:lang="vi-vn">Bàn phím Tizen</label>
    <label xml:lang="zh-cn">Tizen 键盘</label>
    <label xml:lang="zh-hk">Tizen 鍵盤</label>
    <label xml:lang="zh-tw">Tizen 鍵盤</label>
    <icon/>
</ui-application>
</manifest>
